cd2root/__init__.py
cd2root/main.py
cd2root-0.1.6.dist-info/AUTHORS.rst
cd2root-0.1.6.dist-info/LICENSE
cd2root-0.1.6.dist-info/METADATA
cd2root-0.1.6.dist-info/WHEEL
cd2root-0.1.6.dist-info/top_level.txt
cd2root-0.1.6.dist-info/RECORD
