Metadata-Version: 2.1
Name: cd2root
Version: 0.1.6
Summary: Change Working Directory to the Project Root
Author-email: garywei944 <garywei944@gmail.com>
License: MIT license
Project-URL: Homepage, https://github.com/garywei944/python-cd2root
Project-URL: Changelog, https://github.com/garywei944/python-cd2root/blob/main/HISTORY.rst
Project-URL: Bug Tracker, https://github.com/garywei944/python-cd2root/issues
Keywords: cd2root,Working Directory,Project Root,cd
Classifier: Intended Audience :: Developers
Classifier: License :: OSI Approved :: MIT License
Classifier: Natural Language :: English
Classifier: Operating System :: OS Independent
Classifier: Programming Language :: Python :: 3
Classifier: Programming Language :: Python :: 3.8
Classifier: Programming Language :: Python :: 3.9
Classifier: Programming Language :: Python :: 3.10
Requires-Python: >=3.8
License-File: LICENSE
License-File: AUTHORS.rst
Requires-Dist: python-dotenv
Requires-Dist: absl-py
